resumaker/__about__.py
resumaker/__init__.py
resumaker/__main__.py
resumaker/config.py
resumaker/obsolete.py
resumaker/render_resume.py
resumaker/template_str.py
resumaker/utils.py
resumaker/templates/t1/__init__.py
resumaker/templates/t1/resume.cls
resumaker/templates/t1/resume.py
resumaker/templates/t1/template.py
resumaker/templates/t1/tex_template.yml
resumaker/templates/t1/icons/LICENSE
resumaker/templates/t1/icons/github.png
resumaker/templates/t1/icons/linkedin.png
resumaker/templates/t1/icons/mail.png
resumaker/templates/t1/icons/phone.png
resumaker-1.0.0rc4.dist-info/METADATA
resumaker-1.0.0rc4.dist-info/WHEEL
resumaker-1.0.0rc4.dist-info/entry_points.txt
resumaker-1.0.0rc4.dist-info/licenses/AUTHORS.md
resumaker-1.0.0rc4.dist-info/licenses/LICENSE
resumaker-1.0.0rc4.dist-info/RECORD
