Metadata-Version: 2.4
Name: resumaker
Version: 1.0.0rc4
Summary: Effortlessly create multiple, ATS-friendly resumes from a single YAML file with Resumaker.
Project-URL: Homepage, https://github.com/sujaudd1n/resumaker
Project-URL: Documentation, https://github.com/sujaudd1n/resumaker
Project-URL: Issues, https://github.com/sujaudd1n/resumaker/issues
Project-URL: Source, https://github.com/sujaudd1n/resumaker
Author: Md Sujauddin Sekh
License-Expression: MIT
License-File: AUTHORS.md
License-File: LICENSE
Keywords: Resumaker,Resume,Resume Maker
Classifier: Environment :: Console
Classifier: Programming Language :: Python
Classifier: Programming Language :: Python :: 3.8
Classifier: Programming Language :: Python :: 3.9
Classifier: Programming Language :: Python :: 3.10
Classifier: Programming Language :: Python :: 3.11
Classifier: Programming Language :: Python :: 3.12
Classifier: Programming Language :: Python :: 3.13
Classifier: Programming Language :: Python :: Implementation :: CPython
Classifier: Programming Language :: Python :: Implementation :: PyPy
Classifier: Topic :: Text Processing :: Markup :: LaTeX
Requires-Python: >=3.8
Requires-Dist: pyyaml==6.0.2
